README.md
setup.py
halo_app/__init__.py
halo_app/base_util.py
halo_app/bootstrap.py
halo_app/classes.py
halo_app/config.py
halo_app/const.py
halo_app/error.py
halo_app/events.py
halo_app/exceptions.py
halo_app/logs.py
halo_app/models.py
halo_app/pipeline.py
halo_app/reflect.py
halo_app/saga.py
halo_app/security.py
halo_app/settingsx.py
halo_app/ssm.py
halo_app/sys_util.py
halo_app.egg-info/PKG-INFO
halo_app.egg-info/SOURCES.txt
halo_app.egg-info/dependency_links.txt
halo_app.egg-info/requires.txt
halo_app.egg-info/top_level.txt
halo_app/app/__init__.py
halo_app/app/anlytx_filter.py
halo_app/app/bus.py
halo_app/app/business_event.py
halo_app/app/cmd_assembler.py
halo_app/app/command.py
halo_app/app/context.py
halo_app/app/dto.py
halo_app/app/dto_assembler.py
halo_app/app/dto_mapper.py
halo_app/app/engine.py
halo_app/app/err_msg.py
halo_app/app/event.py
halo_app/app/exceptions.py
halo_app/app/exchange.py
halo_app/app/globals.py
halo_app/app/handlers.py
halo_app/app/message.py
halo_app/app/notification.py
halo_app/app/query.py
halo_app/app/query_filters.py
halo_app/app/request.py
halo_app/app/response.py
halo_app/app/result.py
halo_app/app/uow.py
halo_app/app/utilx.py
halo_app/app/view_response.py
halo_app/domain/__init__.py
halo_app/domain/entity.py
halo_app/domain/event.py
halo_app/domain/exceptions.py
halo_app/domain/model.py
halo_app/domain/repository.py
halo_app/domain/service.py
halo_app/entrypoints/__init__.py
halo_app/entrypoints/cli.py
halo_app/entrypoints/client_type.py
halo_app/entrypoints/client_util.py
halo_app/entrypoints/event_consumer.py
halo_app/entrypoints/redis_event_consumer.py
halo_app/infra/__init__.py
halo_app/infra/apis.py
halo_app/infra/cache.py
halo_app/infra/event_publisher.py
halo_app/infra/exceptions.py
halo_app/infra/mail.py
halo_app/infra/notifications.py
halo_app/infra/sql_orm.py
halo_app/infra/sql_repository.py
halo_app/infra/sql_uow.py
halo_app/infra/impl/__init__.py
halo_app/infra/impl/redis_event_publisher.py
halo_app/infra/providers/__init__.py
halo_app/infra/providers/exceptions.py
halo_app/infra/providers/providers.py
halo_app/infra/providers/util.py
